{"stellarexplorer": 0, "Broadway": 1, "MyWritingCompanion": 2, "diceroller": 3, "shimmer_daily": 4, "CribbageScorer": 5, "talkfpl": 6, "WebRewind": 7, "mini_habits": 8, "Talkface_IELTS_Prep": 9, "heygen": 10, "TalentOrg": 11, "social_media_muse": 12, "QuiverQuantitative": 13, "Google_Ads_Shopping_Microsoft_Ads_pay_per_click": 14, "wpinteract": 15, "Man_of_Many": 16, "WordCloud": 17, "SuperchargeMyEV": 18, "smarttsicketsai": 19, "word_counter": 20, "web_scraper": 21, "clinical_trial_radar": 22, "what_to_watch": 23, "hdbcarpark": 24, "sakenowa": 25, "ArtCollection": 26, "dover_outreach": 27, "AusSurfReport": 28, "Planfit": 29, "SASpeedCameras": 30, "website_performance_insights": 31, "hacktrack": 32, "dart": 33, "CTCP": 34, "Horoscopes_by_Inner_Self": 35, "CranePumpsManuals": 36, "themeparkhipster": 37, "find_agency": 38, "CreditYelp": 39, "bramework": 40, "photorealistic": 41, "dev": 42, "decision_journal": 43, "ABCmouse": 44, "C3_Glide": 45, "uberchord": 46, "IndoorPlants": 47, "buildbetter": 48, "portfoliopilot": 49, "kraftful": 50, "Bohita": 51, "competitorppcads": 52, "KalendarAI": 53, "recipe_retrieval": 54, "haulingbuddies": 55, "FinanceTool": 56, "ExchangeTool": 57, "NewsTool": 58, "PolishTool": 59, "CharityTool": 60, "MapTool": 61, "CourseTool": 62, "DataRetrievalTool": 63, "StrologyTool": 64, "NotesTool": 65, "MemoryTool": 66, "LawTool": 67, "ChartTool": 68, "EarthquakeTool": 69, "NASATool": 70, "CompanyInfoTool": 71, "ResumeTool": 72, "MemeTool": 73, "GiftTool": 74, "PDF&URLTool": 75, "VideoSummarizeTool": 76, "MediaModifyTool": 77, "DietTool": 78, "WebsiteTool": 79, "URLTool": 80, "TripTool": 81, "TripAdviceTool": 82, "BookTool": 83, "MediaTool": 84, "PodcastTool": 85, "MusicTool": 86, "GameTool": 87, "WeatherTool": 88, "RestaurantBookingTool": 89, "HouseRentingTool": 90, "HousePurchasingTool": 91, "JobTool": 92, "RepoTool": 93, "ResearchFinder": 94, "ResearchHelper": 95, "SEOTool": 96, "ProductSearch": 97, "Discount": 98, "Review": 99}